[
    {
        "img": "gamespot-one.jpeg",
        "title": "The Best Xbox-Exclusive Games Of 2023",
        "text": "These Xbox console exclusives stood above the rest in 2023.",
        "card-class": "large-ad-one large-card",
        "text-class": "large-text"
    },
    {
        "img": "gamespot-two.jpeg",
        "title": "Something cool. Check it out",
        "text": "These Xbox console exclusives stood above the rest in 2023.",
        "card-class": "large-ad-two large-card",
        "text-class": "large-text"
    },
    {
        "img": "gamespot-three.jpeg",
        "title": "Something cool. Check it out",
        "text": "These Xbox console exclusives stood above the rest in 2023.",
        "card-class": "small-ad-one small-card",
        "text-class": "small-text"
    },
    {
        "img": "gamespot-four.jpeg",
        "title": "Something cool. Check it out",
        "text": "These Xbox console exclusives stood above the rest in 2023.",
        "card-class": "small-ad-two small-card",
        "text-class": "small-text"
    },
    {
        "img": "gamespot-five.jpeg",
        "title": "Something cool. Check it out",
        "text": "These Xbox console exclusives stood above the rest in 2023.",
        "card-class": "small-ad-three small-card",
        "text-class": "small-text"
    },
    {
        "img": "gamespot-six.jpeg",
        "title": "Something cool. Check it out",
        "text": "These Xbox console exclusives stood above the rest in 2023.",
        "card-class": "small-ad-four small-card",
        "text-class": "small-text"
    },
    {
        "img": "gamespot-seven.jpeg",
        "title": "Something cool. Check it out",
        "text": "These Xbox console exclusives stood above the rest in 2023.",
        "card-class": "small-ad-five small-card",
        "text-class": "small-text"
    },
    {
        "img": "gamespot-eight.jpeg",
        "title": "Something cool. Check it out",
        "text": "These Xbox console exclusives stood above the rest in 2023.",
        "card-class": "small-ad-six small-card",
        "text-class": "small-text"
    },
    {
        "img": "gamespot-nine.jpeg",
        "title": "Something cool. Check it out",
        "text": "These Xbox console exclusives stood above the rest in 2023.",
        "card-class": "small-ad-seven small-card",
        "text-class": "small-text"
    },
    {
        "img": "gamespot-ten.jpeg",
        "title": "Something cool. Check it out",
        "text": "These Xbox console exclusives stood above the rest in 2023.",
        "card-class": "small-ad-eight small-card",
        "text-class": "small-text"
    }
]